Metadata-Version: 1.0
Name: magetool-zhengfeng
Version: 0.1.0
Summary: time and path tool
Home-page: https://github.com/fengmm521/pipProject
Author: zhengfeng
Author-email: mage@woodcol.com
License: MIT Licence
Keywords: pip,pathtool,timetool,magetool_zhengfeng,mage
Platform: any
